[
  {
    "id": "1780543654226y0pqv",
    "timestamp": "2026-06-04T03:27:34.226Z",
    "date": "04/06/2026",
    "time": "06:27",
    "aircraft": "HZ-AK35",
    "reporter": "AHMED ALGHAMDI",
    "findings": [
      {
        "category": "GENERAL CABIN     ",
        "subCategory": "N/A               ",
        "description": "ANC                                                         ",
        "remarks": "                         ",
        "photoUrl": "https://i.ibb.co/kVkKXZdh/ec0bcd77ebce.jpg"
      }
    ]
  }
]